drb/topics/sentinel5/__init__.py
drb/topics/sentinel5/_version.py
drb/topics/sentinel5/cortex.yml
drb/topics/sentinel5/auxiliary/__init__.py
drb/topics/sentinel5/auxiliary/cortex.yml
drb/topics/sentinel5/level1/__init__.py
drb/topics/sentinel5/level1/cortex.yml
drb/topics/sentinel5/level2/__init__.py
drb/topics/sentinel5/level2/cortex.yml
drb_topic_sentinel5-1.1.1.data/data/requirements.txt
drb_topic_sentinel5-1.1.1.dist-info/METADATA
drb_topic_sentinel5-1.1.1.dist-info/WHEEL
drb_topic_sentinel5-1.1.1.dist-info/entry_points.txt
drb_topic_sentinel5-1.1.1.dist-info/top_level.txt
drb_topic_sentinel5-1.1.1.dist-info/RECORD
