Metadata-Version: 2.1
Name: drb-topic-sentinel5
Version: 1.1.1
Summary: sentinel-5 topic for DRB Python
Home-page: https://gitlab.com/drb-python/topics/sentinel-5
Author: GAEL Systems
Author-email: drb-python@gael.fr
License: UNKNOWN
Platform: UNKNOWN
Classifier: Programming Language :: Python :: 3.8
Classifier: License :: OSI Approved :: Apache Software License
Classifier: Programming Language :: Python :: 3.8
Requires-Python: >=3.8
Requires-Dist: drb (~=2.0.3)
Requires-Dist: drb-driver-netcdf (~=1.1.0)
